spb/__init__.py
spb/__main__.py
spb/cli.py
spb/session.py
spb/spb_logger.py
spb/cli_core/__init__.py
spb/cli_core/helper.py
spb/cli_core/utils.py
spb/cli_core/commands/__init__.py
spb/cli_core/commands/label_data.py
spb/cli_core/commands/project.py
spb/command/__init__.py
spb/command/builder.py
spb/command/commands.py
spb/datauri/__init__.py
spb/datauri/exceptions.py
spb/exceptions/__init__.py
spb/exceptions/exceptions.py
spb/models/__init__.py
spb/models/data.py
spb/models/label.py
spb/models/project.py
spb/orm/__init__.py
spb/orm/loading.py
spb/orm/manager.py
spb/orm/model.py
spb/orm/query.py
spb/orm/type.py
spb/orm/utils.py
spb_cli-0.0.26.dist-info/METADATA
spb_cli-0.0.26.dist-info/WHEEL
spb_cli-0.0.26.dist-info/entry_points.txt
spb_cli-0.0.26.dist-info/top_level.txt
spb_cli-0.0.26.dist-info/RECORD
