Metadata-Version: 2.1
Name: spb-cli
Version: 0.0.26
Summary: Suite Standard Library
Home-page: https://github.com/Superb-AI-Suite/cool-tree.git
Author: Superb AI
Author-email: support@superb-ai.com
License: MIT
Platform: UNKNOWN
Classifier: Development Status :: 1 - Planning
Classifier: Intended Audience :: Developers
Classifier: Topic :: Software Development :: Libraries
Classifier: License :: OSI Approved :: MIT License
Classifier: Programming Language :: Python :: 3.6
Requires-Dist: bleach (==3.1.5)
Requires-Dist: certifi (==2020.4.5.1)
Requires-Dist: chardet (==3.0.4)
Requires-Dist: click (==7.1.2)
Requires-Dist: colorama (==0.4.3)
Requires-Dist: commonmark (==0.9.1)
Requires-Dist: docutils (==0.16)
Requires-Dist: idna (==2.9)
Requires-Dist: keyring (==21.2.1)
Requires-Dist: packaging (==20.4)
Requires-Dist: pkginfo (==1.5.0.1)
Requires-Dist: pprintpp (==0.4.0)
Requires-Dist: pygments (==2.6.1)
Requires-Dist: pyparsing (==2.4.7)
Requires-Dist: python-datauri (==0.2.8)
Requires-Dist: readme-renderer (==26.0)
Requires-Dist: requests (==2.23.0)
Requires-Dist: requests-toolbelt (==0.9.1)
Requires-Dist: rich (==1.2.3)
Requires-Dist: six (==1.15.0)
Requires-Dist: stringcase (==1.2.0)
Requires-Dist: tqdm (==4.46.0)
Requires-Dist: twine (==3.1.1)
Requires-Dist: typing-extensions (==3.7.4.2)
Requires-Dist: urllib3 (==1.25.9)
Requires-Dist: webencodings (==0.5.1)
Requires-Dist: zipp (==3.1.0)
Requires-Dist: importlib-metadata (==1.6.0) ; python_version < "3.8"
